README.rst
setup.py
apigen/__init__.py
apigen/test/__init__.py
apigen/test/test_apigen.py
fluent_http_apigen.egg-info/PKG-INFO
fluent_http_apigen.egg-info/SOURCES.txt
fluent_http_apigen.egg-info/dependency_links.txt
fluent_http_apigen.egg-info/entry_points.txt
fluent_http_apigen.egg-info/not-zip-safe
fluent_http_apigen.egg-info/requires.txt
fluent_http_apigen.egg-info/top_level.txt