Metadata-Version: 2.1
Name: fluent-http-apigen
Version: 0.3.0
Summary: App generate HTTP documentation from fluent-http code
Home-page: https://github.com/ICIJ/fluent-http-apigen
Author: Sabrina Sahli, Bruno Thomas
Author-email: sahli.sabrina@gmail.com, bthomas@icij.org
License: LICENSE.txt
Keywords: icij,fluent-http,documentation
Platform: UNKNOWN
Classifier: Programming Language :: Python
Provides-Extra: dev
